make_it_soft_provider-0.9.5.post202103312318.data/scripts/make-it-soft-provider
makeitsoft/__init__.py
makeitsoft/app_scaffolder.py
makeitsoft/app_selector.py
makeitsoft/logger.py
makeitsoft/main.py
makeitsoft/service_operation.py
makeitsoft/utils.py
makeitsoft/conf/business-solution.yml
makeitsoft/locales/messages.pot
makeitsoft/locales/en/LC_MESSAGES/messages.mo
makeitsoft/locales/en/LC_MESSAGES/messages.po
makeitsoft/locales/fr/LC_MESSAGES/messages.mo
makeitsoft/locales/fr/LC_MESSAGES/messages.po
makeitsoft/templates/conf.general.yml
makeitsoft/templates/service.sh
makeitsoft/templates/dolibarr/docker-compose.yml
makeitsoft/templates/ehour/docker-compose.yml
makeitsoft/templates/maarch-courrier/docker-compose.yml
makeitsoft/templates/mantis/docker-compose.yml
makeitsoft/templates/odoo/docker-compose.yml
makeitsoft/templates/openproject/docker-compose.yml
makeitsoft/templates/osticket/docker-compose.yml
makeitsoft/templates/owncloud/docker-compose.yml
makeitsoft/templates/portail-solutions/docker-compose.yml
makeitsoft/templates/portail-solutions/apps/backend/config/config.json
makeitsoft/templates/portail-solutions/apps/backend/logos/dolibarr.png
makeitsoft/templates/portail-solutions/apps/backend/logos/ehour.png
makeitsoft/templates/portail-solutions/apps/backend/logos/maarch-courrier.png
makeitsoft/templates/portail-solutions/apps/backend/logos/mantis.png
makeitsoft/templates/portail-solutions/apps/backend/logos/odoo.png
makeitsoft/templates/portail-solutions/apps/backend/logos/openproject.png
makeitsoft/templates/portail-solutions/apps/backend/logos/osticket.png
makeitsoft/templates/portail-solutions/apps/backend/logos/owncloud.png
makeitsoft/templates/portail-solutions/apps/frontend/endpoint.json
makeitsoft/templates/portail-solutions/apps/frontend/config/domain-config.bat
makeitsoft/templates/portail-solutions/apps/frontend/lang/lang-available.json
makeitsoft/templates/portail-solutions/apps/frontend/lang/lang-en.json
make_it_soft_provider-0.9.5.post202103312318.dist-info/METADATA
make_it_soft_provider-0.9.5.post202103312318.dist-info/WHEEL
make_it_soft_provider-0.9.5.post202103312318.dist-info/top_level.txt
make_it_soft_provider-0.9.5.post202103312318.dist-info/RECORD
